hotfunc.py
hotfunc-0.0.1.dist-info/LICENSE.txt
hotfunc-0.0.1.dist-info/METADATA
hotfunc-0.0.1.dist-info/WHEEL
hotfunc-0.0.1.dist-info/top_level.txt
hotfunc-0.0.1.dist-info/RECORD
