Metadata-Version: 2.1
Name: hotfunc
Version: 0.0.1
Summary: Make functions hot-reloadable with a decorator
Author-email: Michał Szajbe <michal.szajbe@gmail.com>
License: MIT License
Project-URL: Homepage, https://github.com/szajbus/hotfunc
Keywords: hotreload
Classifier: Development Status :: 3 - Alpha
Classifier: Programming Language :: Python
Requires-Python: >=3.4
License-File: LICENSE.txt
